{"device_model":"SM-G9350","fb_adgroup_id":null,"click_time_selected_timezone":null,"download_time_selected_timezone":"2017-09-12 20:07:00.000+0000","download_time":"2017-09-12 20:07:00","operator":"UNICOM HK","af_keywords":null,"attributed_touch_time":null,"click_time":null,"agency":null,"ip":"1.1.1.1","cost_per_install":null,"fb_campaign_id":null,"imei":null,"is_retargeting":false,"app_name":"Aero Strike","re_targeting_conversion_type":null,"android_id":null,"city":"New Kowloon","af_sub1":null,"af_sub2":null,"event_value":"{\"event_value\":\"1004, , , \"}","af_sub3":null,"fb_adset_name":null,"af_sub4":null,"customer_user_id":null,"mac":null,"af_sub5":null,"install_time_selected_timezone":"2017-09-12 20:08:28.734+0000","campaign":null,"event_name":"start","event_time_selected_timezone":"2017-09-25 10:04:39.481+0000","currency":"USD","install_time":"2017-09-12 20:08:28","fb_adgroup_name":null,"attributed_touch_type":null,"event_time":"2017-09-25 10:04:39","platform":"android","sdk_version":"6.0","appsflyer_device_id":"1505246869281-829512728607570328","selected_currency":"USD","wifi":true,"advertising_id":"7c55ca8c-7331-4de2-b354-ee4ef9da40c1","media_source":"Organic","country_code":"HK","http_referrer":null,"fb_campaign_name":null,"bundle_id":"com.joymax.fr","click_url":null,"carrier":"3","language":"中文","app_id":"com.joymax.fr","app_version":"1.3.1","attribution_type":"organic","af_siteid":null,"os_version":"6.0.1","fb_adset_id":null,"device_brand":"samsung","revenue_in_selected_currency":null,"event_type":"in-app-event"}